sigmaepsilon/core/__init__.py
sigmaepsilon/core/abstract.py
sigmaepsilon/core/acp.py
sigmaepsilon/core/alphabet.py
sigmaepsilon/core/attr.py
sigmaepsilon/core/colors.py
sigmaepsilon/core/config.py
sigmaepsilon/core/cp.py
sigmaepsilon/core/decorate.py
sigmaepsilon/core/downloads.py
sigmaepsilon/core/exceptions.py
sigmaepsilon/core/formatting.py
sigmaepsilon/core/infix.py
sigmaepsilon/core/io.py
sigmaepsilon/core/kwargtools.py
sigmaepsilon/core/meta.py
sigmaepsilon/core/misc.py
sigmaepsilon/core/osutils.py
sigmaepsilon/core/signature.py
sigmaepsilon/core/testing.py
sigmaepsilon/core/thirdparty.py
sigmaepsilon/core/typing.py
sigmaepsilon/core/warning.py
sigmaepsilon/core/wrapping.py
sigmaepsilon_core-1.2.2.dist-info/LICENSE
sigmaepsilon_core-1.2.2.dist-info/METADATA
sigmaepsilon_core-1.2.2.dist-info/WHEEL
sigmaepsilon_core-1.2.2.dist-info/RECORD
