Metadata-Version: 2.1
Name: sigmaepsilon.core
Version: 1.2.2
Summary: Common developer utilities for Python projects.
Home-page: https://github.com/sigma-epsilon/sigmaepsilon.core
License: MIT
Author: Bence Balogh
Author-email: bencebalogh@sigmaepsilon.com
Maintainer: Bence Balogh
Maintainer-email: bencebalogh@sigmaepsilon.com
Requires-Python: >=3.10,<4.0
Classifier: Development Status :: 5 - Production/Stable
Classifier: License :: OSI Approved :: MIT License
Classifier: Operating System :: OS Independent
Classifier: Programming Language :: Python :: 3
Classifier: Programming Language :: Python :: 3.10
Classifier: Programming Language :: Python :: 3.11
Classifier: Programming Language :: Python :: 3.12
Classifier: Programming Language :: Python :: 3.13
Classifier: Programming Language :: Python :: 3 :: Only
Requires-Dist: appdirs
Requires-Dist: six
Requires-Dist: toml
Project-URL: Documentation, https://sigmaepsiloncore.readthedocs.io/en/latest/?badge=latest
Project-URL: Repository, https://github.com/sigma-epsilon/sigmaepsilon.core
